{
    "b1": {
        "type": "devices",
        "message": [
            {
                "ieeeAddr": "0x00124b0018ed3ded",
                "type": "Coordinator"
            },
            {
                "ieeeAddr": "0x00158d00028f7fb5",
                "type": "EndDevice",
                "model": "WXKG03LM",
                "friendly_name": "large switch",
                "nwkAddr": 65359,
                "manufId": 4151,
                "manufName": "LUMI",
                "powerSource": "Battery",
                "modelId": "lumi.remote.b186acn01\u0000\u0000\u0000"
            },
            {
                "ieeeAddr": "0x00158d00028cad58",
                "type": "EndDevice",
                "model": "WXKG03LM",
                "friendly_name": "entrance light",
                "nwkAddr": 12023,
                "manufId": 4151,
                "manufName": "LUMI",
                "powerSource": "Battery",
                "modelId": "lumi.remote.b186acn01\u0000\u0000\u0000"
            },
            {
                "ieeeAddr": "0x00158d0001e7a12b",
                "type": "EndDevice",
                "model": "WXKG11LM",
                "friendly_name": "sunrise",
                "nwkAddr": 15211,
                "manufId": 4151,
                "manufName": "LUMI",
                "powerSource": "Battery",
                "modelId": "lumi.remote.b1acn01\u0000\u0000\u0000\u0000\u0000\u0000"
            },
            {
                "ieeeAddr": "0x00158d000232c52c",
                "type": "EndDevice",
                "model": "MCCGQ11LM",
                "friendly_name": "entrance door",
                "nwkAddr": 49162,
                "manufId": 4151,
                "manufName": "LUMI",
                "powerSource": "Battery",
                "modelId": "lumi.sensor_magnet.aq2"
            },
            {
                "ieeeAddr": "0x00158d0002518c83",
                "type": "EndDevice",
                "model": "MCCGQ11LM",
                "friendly_name": "balcony door",
                "nwkAddr": 31777,
                "manufId": 4151,
                "manufName": "LUMI",
                "powerSource": "Battery",
                "modelId": "lumi.sensor_magnet.aq2"
            },
            {
                "ieeeAddr": "0x00158d00026ecd6a",
                "type": "EndDevice",
                "model": "WSDCGQ11LM",
                "friendly_name": "0x00158d00026ecd6a",
                "nwkAddr": 6880,
                "manufId": 4151,
                "manufName": "LUMI",
                "powerSource": "Battery",
                "modelId": "lumi.weather"
            },
            {
                "ieeeAddr": "0x00158d000237df83",
                "type": "EndDevice",
                "model": "WSDCGQ11LM",
                "friendly_name": "0x00158d000237df83",
                "nwkAddr": 24210,
                "manufId": 4151,
                "manufName": "LUMI",
                "powerSource": "Battery",
                "modelId": "lumi.weather"
            },
            {
                "ieeeAddr": "0x00124b0018ecdf32",
                "type": "Router",
                "model": "CC2530.ROUTER",
                "friendly_name": "router 1",
                "nwkAddr": 31431,
                "manufId": 4447,
                "manufName": "LUMI",
                "powerSource": "Mains (single phase)",
                "modelId": "lumi.router"
            },
            {
                "ieeeAddr": "0x00158d00029078a2",
                "type": "EndDevice",
                "model": "WXKG12LM",
                "friendly_name": "large switch hass",
                "nwkAddr": 6009,
                "manufId": 4151,
                "manufName": "LUMI",
                "powerSource": "Battery",
                "modelId": "lumi.sensor_swit"
            },
            {
                "ieeeAddr": "0x00158d0002725dc1",
                "type": "EndDevice",
                "model": "MCCGQ11LM",
                "friendly_name": "bathroom window",
                "nwkAddr": 47893,
                "manufId": 4151,
                "manufName": "LUMI",
                "powerSource": "Battery",
                "modelId": "lumi.sensor_magnet.aq2"
            },
            {
                "ieeeAddr": "0x00158d0002753dec",
                "type": "EndDevice",
                "model": "RTCGQ11LM",
                "friendly_name": "kitchen move",
                "nwkAddr": 14156,
                "manufId": 4151,
                "manufName": "LUMI",
                "powerSource": "Battery",
                "modelId": "lumi.sensor_motion.aq2"
            },
            {
                "ieeeAddr": "0x0017880103291b35",
                "type": "EndDevice",
                "model": "9290012607",
                "friendly_name": "hue motion",
                "nwkAddr": 20946,
                "manufId": 4107,
                "manufName": "Philips",
                "powerSource": "Battery",
                "modelId": "SML001"
            },
            {
                "ieeeAddr": "0x00158d0001eb9b32",
                "type": "EndDevice",
                "model": "WXKG12LM",
                "friendly_name": "retrolight1",
                "nwkAddr": 49186,
                "manufId": 4151,
                "manufName": "LUMI",
                "powerSource": "Battery",
                "modelId": "lumi.sensor_swit"
            },
            {
                "ieeeAddr": "0x00158d0002a2c21c",
                "type": "EndDevice",
                "model": "WXKG12LM",
                "friendly_name": "retrolight2",
                "nwkAddr": 50963,
                "manufId": 4151,
                "manufName": "LUMI",
                "powerSource": "Battery",
                "modelId": "lumi.sensor_swit"
            },
            {
                "ieeeAddr": "0x00158d0001eb81c7",
                "type": "EndDevice",
                "model": "WXKG12LM",
                "friendly_name": "tree",
                "nwkAddr": 18462,
                "manufId": 4151,
                "manufName": "LUMI",
                "powerSource": "Battery",
                "modelId": "lumi.sensor_swit"
            },
            {
                "ieeeAddr": "0x00158d0001eb8fc9",
                "type": "EndDevice",
                "model": "WXKG12LM",
                "friendly_name": "button test 4",
                "nwkAddr": 50641,
                "manufId": 4151,
                "manufName": "LUMI",
                "powerSource": "Battery",
                "modelId": "lumi.sensor_swit"
            },
            {
                "ieeeAddr": "0x00158d0002a51beb",
                "type": "EndDevice",
                "model": "DJT11LM",
                "friendly_name": "0x00158d0002a51beb",
                "nwkAddr": 756,
                "manufId": 4151,
                "modelId": "lumi.vibration.aq1"
            },
            {
                "ieeeAddr": "0x00158d0002a4f51d",
                "type": "EndDevice",
                "model": "DJT11LM",
                "friendly_name": "0x00158d0002a4f51d",
                "nwkAddr": 58794,
                "manufId": 4151,
                "manufName": "LUMI",
                "powerSource": "Battery",
                "modelId": "lumi.vibration.aq1"
            },
            {
                "ieeeAddr": "0x00158d0002a51bee",
                "type": "EndDevice",
                "model": "DJT11LM",
                "friendly_name": "0x00158d0002a51bee",
                "nwkAddr": 8837,
                "manufId": 4151,
                "manufName": "LUMI",
                "powerSource": "Battery",
                "modelId": "lumi.vibration.aq1"
            },
            {
                "ieeeAddr": "0x00158d0002a4f5cc",
                "type": "EndDevice",
                "friendly_name": "0x00158d0002a4f5cc",
                "nwkAddr": 5511,
                "manufId": 4151
            },
            {
                "ieeeAddr": "0x00158d0002a549ff",
                "type": "EndDevice",
                "friendly_name": "0x00158d0002a549ff",
                "nwkAddr": 21206,
                "manufId": 4151
            },
            {
                "ieeeAddr": "0x00158d0002a4f538",
                "type": "EndDevice",
                "friendly_name": "0x00158d0002a4f538",
                "nwkAddr": 8012,
                "manufId": 4151
            },
            {
                "ieeeAddr": "0x00158d0002b45474",
                "type": "EndDevice",
                "model": "RTCGQ11LM",
                "friendly_name": "stairs down move",
                "nwkAddr": 56047,
                "manufId": 4151,
                "manufName": "LUMI",
                "powerSource": "Battery",
                "modelId": "lumi.sensor_motion.aq2"
            }
        ]
    },
    "b2": {
        "type": "devices",
        "message": [
            {
                "ieeeAddr": "0x00124b0018ed23a5",
                "type": "Coordinator"
            },
            {
                "ieeeAddr": "0x00158d000255fb8b",
                "type": "EndDevice",
                "model": "SJCGQ11LM",
                "friendly_name": "floody",
                "nwkAddr": 59886,
                "manufId": 4151,
                "manufName": "LUMI",
                "powerSource": "Battery",
                "modelId": "lumi.sensor_wleak.aq1"
            },
            {
                "ieeeAddr": "0x00158d0002a4f61e",
                "type": "EndDevice",
                "model": "DJT11LM",
                "friendly_name": "desk motion",
                "nwkAddr": 16144,
                "manufId": 4151,
                "manufName": "LUMI",
                "powerSource": "Battery",
                "modelId": "lumi.vibration.aq1"
            },
            {
                "ieeeAddr": "0x00158d0002476b04",
                "type": "EndDevice",
                "model": "WSDCGQ11LM",
                "friendly_name": "desk weather",
                "nwkAddr": 1463,
                "manufId": 4151,
                "manufName": "LUMI",
                "powerSource": "Battery",
                "modelId": "lumi.weather"
            },
            {
                "ieeeAddr": "0x0017880103291b35",
                "type": "EndDevice",
                "model": "9290012607",
                "friendly_name": "stairs up move",
                "nwkAddr": 20946,
                "manufId": 4107,
                "manufName": "Philips",
                "powerSource": "Battery",
                "modelId": "SML001"
            },
            {
                "ieeeAddr": "0x00158d0002b45474",
                "type": "EndDevice",
                "model": "RTCGQ11LM",
                "friendly_name": "0x00158d0002b45474",
                "nwkAddr": 40760,
                "manufId": 4151,
                "manufName": "LUMI",
                "powerSource": "Battery",
                "modelId": "lumi.sensor_motion.aq2"
            },
            {
                "ieeeAddr": "0x00158d00024b3e45",
                "type": "EndDevice",
                "model": "WXKG03LM",
                "friendly_name": "dining switch",
                "nwkAddr": 27049,
                "manufId": 4151,
                "manufName": "LUMI",
                "powerSource": "Battery",
                "modelId": "lumi.sensor_86sw1\u0000lu"
            },
            {
                "ieeeAddr": "0x00158d00028f8531",
                "type": "EndDevice",
                "model": "MFKZQ01LM",
                "friendly_name": "cube",
                "nwkAddr": 10712,
                "manufId": 4151,
                "manufName": "LUMI",
                "powerSource": "Battery",
                "modelId": "lumi.sensor_cube"
            },
            {
                "ieeeAddr": "0x00158d0001ef6374",
                "type": "EndDevice",
                "model": "WXKG11LM",
                "friendly_name": "bed light button",
                "nwkAddr": 17468,
                "manufId": 4151,
                "manufName": "LUMI",
                "powerSource": "Battery",
                "modelId": "lumi.remote.b1acn01\u0000\u0000\u0000\u0000\u0000\u0000"
            },
            {
                "ieeeAddr": "0x00158d00026ecd6a",
                "type": "EndDevice",
                "model": "WSDCGQ11LM",
                "friendly_name": "bed weather",
                "nwkAddr": 40828,
                "manufId": 4151,
                "manufName": "LUMI",
                "powerSource": "Battery",
                "modelId": "lumi.weather"
            },
            {
                "ieeeAddr": "0x00158d000237df83",
                "type": "EndDevice",
                "model": "WSDCGQ11LM",
                "friendly_name": "balcony weather",
                "nwkAddr": 46489,
                "manufId": 4151,
                "manufName": "LUMI",
                "powerSource": "Battery",
                "modelId": "lumi.weather"
            },
            {
                "ieeeAddr": "0x00158d000192dd3e",
                "type": "EndDevice",
                "model": "SPZB0001",
                "friendly_name": "living heat",
                "nwkAddr": 23647,
                "manufId": 4151,
                "manufName": "Eurotronic",
                "powerSource": "Battery",
                "modelId": "SPZB0001"
            },
            {
                "ieeeAddr": "0x00158d000272623b",
                "type": "EndDevice",
                "model": "MCCGQ11LM",
                "friendly_name": "living window left",
                "nwkAddr": 21540,
                "manufId": 4151,
                "manufName": "LUMI",
                "powerSource": "Battery",
                "modelId": "lumi.sensor_magnet.aq2",
                "hwVersion": 2,
                "swBuildId": "3000-0001",
                "dateCode": "20161128"
            },
            {
                "ieeeAddr": "0x00158d0002760208",
                "type": "EndDevice",
                "model": "MCCGQ11LM",
                "friendly_name": "living window right",
                "nwkAddr": 15,
                "manufId": 4151,
                "manufName": "LUMI",
                "powerSource": "Battery",
                "modelId": "lumi.sensor_magnet.aq2",
                "hwVersion": 2,
                "swBuildId": "3000-0001",
                "dateCode": "20161128"
            }
        ]
    }
}